tdrpa/actionblocks/a.pyd
tdrpa/actionblocks/b.pyd
tdrpa/actionblocks/c.pyd
tdrpa_actionblocks-0.0.4.dist-info/METADATA
tdrpa_actionblocks-0.0.4.dist-info/WHEEL
tdrpa_actionblocks-0.0.4.dist-info/top_level.txt
tdrpa_actionblocks-0.0.4.dist-info/RECORD
